Metadata-Version: 1.1
Name: csscompressor
Version: 0.9.3
Summary: A python port of YUI CSS Compressor
Home-page: http://github.com/sprymix/csscompressor
Author: Yury Selivanov
Author-email: info@sprymix.com
License: BSD
Platform: UNKNOWN
Classifier: Development Status :: 5 - Production/Stable
Classifier: Intended Audience :: Developers
Classifier: License :: OSI Approved :: BSD License
Classifier: Operating System :: OS Independent
Classifier: Programming Language :: Python
Classifier: Programming Language :: Python :: 3
Classifier: Programming Language :: Python :: 2.7
Classifier: Programming Language :: Python :: 2.6
Classifier: Topic :: Software Development :: Build Tools
Classifier: Topic :: Text Processing :: General
Classifier: Topic :: Utilities
